{
    "00": "Does Not Apply",
    "11": "Building",
    "12": "Personal Property",
    "13": "Building and Personal Property Combined",
    "35": "Fire Peril - Contents Susceptibility Group A - Low",
    "36": "Fire Peril - Contents Susceptibility Group B - High",
    "37": "Fire Peril - Contents Susceptibility Group C - Average",
    "44": "Time Element - Income coverage (a.k.a. business income with extra expense) options: Earnings including rents and extra expense",
    "45": "Time Element - Income coverage (a.k.a. business income with extra expense) options: Earnings other than rents and extra expense",
    "46": "Time Element - Income coverage (a.k.a. business income with extra expense) options: Rents and extra expense",
    "47": "Time Element - Earnings coverage (a.k.a. business income without extra expense) options: Earnings including rents",
    "48": "Time Element - Earnings coverage (a.k.a. business income without extra expense) options: Earnings other than rents",
    "49": "Time Element - Earnings coverage (a.k.a. business income without extra expense) options: Rents only",
    "40": "Time Element - All Other",
    "41": "Time Element - Income coverage (earnings and extra expense combined)",
    "43": "Time Element - Extra expense",
    "70": "Stock",
    "71": "Computers",
    "72": "Mobile Equipment",
    "73": "Hay, Straw, and Fodder Coverage",
    "74": "Livestock Coverage",
    "75": "Poultry Coverage",
    "99": "All Other"
}