{
    "0":"Does not apply",
    "1":"Certified acts of terrorism not excluded / non-certified acts of terrorism not excluded",
    "2":"Certified acts of terrorism not excluded / non-certified acts of terrorism arising from nuclear, biological, or chemical events excluded",
    "3":"Certified acts of terrorism not excluded / non-certified acts of terrorism excluded, subject to limitations",
    "4a":"Certified terrorism loss excluded a / non-certified acts of terrorism not excluded",
    "5a":"Certified terrorism loss excluded a / non-certified acts of terrorism arising from nuclear, biological, or chemical events excluded",
    "6a":"Certified terrorism loss excluded a / non-certified acts of terrorism excluded a"
}